qiskit_terra-0.46.3.dist-info/LICENSE.txt
qiskit_terra-0.46.3.dist-info/METADATA
qiskit_terra-0.46.3.dist-info/entry_points.txt
qiskit_terra-0.46.3.dist-info/RECORD
qiskit_terra-0.46.3.dist-info/WHEEL
qiskit_terra-0.46.3.dist-info/top_level.txt
qiskit/version.py
qiskit/_numpy_compat.py
qiskit/_accelerate.abi3.so
qiskit/_qasm2.abi3.so
qiskit/exceptions.py
qiskit/execute_function.py
qiskit/namespace.py
qiskit/__init__.py
qiskit/user_config.py
qiskit/VERSION.txt
qiskit/transpiler/fencedobjs.py
qiskit/transpiler/layout.py
qiskit/transpiler/instruction_durations.py
qiskit/transpiler/passmanager_config.py
qiskit/transpiler/basepasses.py
qiskit/transpiler/exceptions.py
qiskit/transpiler/coupling.py
qiskit/transpiler/passmanager.py
qiskit/transpiler/propertyset.py
qiskit/transpiler/timing_constraints.py
qiskit/transpiler/runningpassmanager.py
qiskit/transpiler/__init__.py
qiskit/transpiler/target.py
qiskit/transpiler/synthesis/graysynth.py
qiskit/transpiler/synthesis/__init__.py
qiskit/transpiler/synthesis/aqc/__init__.py
qiskit/transpiler/preset_passmanagers/builtin_plugins.py
qiskit/transpiler/preset_passmanagers/level1.py
qiskit/transpiler/preset_passmanagers/plugin.py
qiskit/transpiler/preset_passmanagers/level3.py
qiskit/transpiler/preset_passmanagers/level2.py
qiskit/transpiler/preset_passmanagers/level0.py
qiskit/transpiler/preset_passmanagers/__init__.py
qiskit/transpiler/preset_passmanagers/common.py
qiskit/transpiler/passes/__init__.py
qiskit/transpiler/passes/optimization/consolidate_blocks.py
qiskit/transpiler/passes/optimization/optimize_1q_gates.py
qiskit/transpiler/passes/optimization/optimize_1q_commutation.py
qiskit/transpiler/passes/optimization/commutative_inverse_cancellation.py
qiskit/transpiler/passes/optimization/collect_and_collapse.py
qiskit/transpiler/passes/optimization/collect_cliffords.py
qiskit/transpiler/passes/optimization/optimize_swap_before_measure.py
qiskit/transpiler/passes/optimization/hoare_opt.py
qiskit/transpiler/passes/optimization/remove_reset_in_zero_state.py
qiskit/transpiler/passes/optimization/collect_1q_runs.py
qiskit/transpiler/passes/optimization/collect_linear_functions.py
